<?xml version="1.0" encoding="UTF-8"?>
<xmi:XMI xmi:version="2.0" xmlns:xmi="http://www.omg.org/XMI" xmlns:TalendProperties="http://www.talend.org/properties">
  <TalendProperties:Property xmi:id="_EGOFIDSPEe-dAdLdqnwK-w" id="_EGM3ADSPEe-dAdLdqnwK-w" label="TalendDataGenerator" version="0.1" item="_EGOFIjSPEe-dAdLdqnwK-w">
    <author href="../../../talend.project#_DFC8ADSPEe-dAdLdqnwK-w"/>
    <additionalProperties xmi:id="_EGULwDSPEe-dAdLdqnwK-w" key="created_product_fullname" value="Talend Open Studio for Data Integration"/>
    <additionalProperties xmi:id="_EGULwTSPEe-dAdLdqnwK-w" key="created_product_version" value="8.0.1.20211109_1610"/>
    <additionalProperties xmi:id="_EGULwjSPEe-dAdLdqnwK-w" key="created_date" value="2024-06-27T16:10:53.180+0200"/>
    <additionalProperties xmi:id="_EGULwzSPEe-dAdLdqnwK-w" key="modified_product_fullname" value="Talend Open Studio for Data Integration"/>
    <additionalProperties xmi:id="_EGULxDSPEe-dAdLdqnwK-w" key="modified_product_version" value="8.0.1.20211109_1610"/>
    <additionalProperties xmi:id="_EGULxTSPEe-dAdLdqnwK-w" key="modified_date" value="2024-06-27T16:10:53.180+0200"/>
  </TalendProperties:Property>
  <TalendProperties:ItemState xmi:id="_EGOFITSPEe-dAdLdqnwK-w" path="system"/>
  <TalendProperties:RoutineItem xmi:id="_EGOFIjSPEe-dAdLdqnwK-w" property="_EGOFIDSPEe-dAdLdqnwK-w" state="_EGOFITSPEe-dAdLdqnwK-w" builtIn="true">
    <content href="TalendDataGenerator_0.1.item#/"/>
  </TalendProperties:RoutineItem>
</xmi:XMI>
