<?xml version="1.0" encoding="UTF-8"?>
<xmi:XMI xmi:version="2.0" xmlns:xmi="http://www.omg.org/XMI" xmlns:TalendProperties="http://www.talend.org/properties">
  <TalendProperties:Property xmi:id="_ET0cQDSPEe-dAdLdqnwK-w" id="_ETz1MDSPEe-dAdLdqnwK-w" label="TeradataDropTargetTable" version="0.1" item="_ET0cQjSPEe-dAdLdqnwK-w">
    <author href="../../../talend.project#_DFC8ADSPEe-dAdLdqnwK-w"/>
    <additionalProperties xmi:id="_ET4GoDSPEe-dAdLdqnwK-w" key="created_product_fullname" value="Talend Open Studio for Data Integration"/>
    <additionalProperties xmi:id="_ET4GoTSPEe-dAdLdqnwK-w" key="created_product_version" value="8.0.1.20211109_1610"/>
    <additionalProperties xmi:id="_ET4GojSPEe-dAdLdqnwK-w" key="created_date" value="2024-06-27T16:10:54.599+0200"/>
    <additionalProperties xmi:id="_ET4GozSPEe-dAdLdqnwK-w" key="modified_product_fullname" value="Talend Open Studio for Data Integration"/>
    <additionalProperties xmi:id="_ET4GpDSPEe-dAdLdqnwK-w" key="modified_product_version" value="8.0.1.20211109_1610"/>
    <additionalProperties xmi:id="_ET4GpTSPEe-dAdLdqnwK-w" key="modified_date" value="2024-06-27T16:10:54.599+0200"/>
  </TalendProperties:Property>
  <TalendProperties:ItemState xmi:id="_ET0cQTSPEe-dAdLdqnwK-w" path="Teradata/system"/>
  <TalendProperties:SQLPatternItem xmi:id="_ET0cQjSPEe-dAdLdqnwK-w" property="_ET0cQDSPEe-dAdLdqnwK-w" state="_ET0cQTSPEe-dAdLdqnwK-w" system="true" eltName="Teradata">
    <content href="TeradataDropTargetTable_0.1.item#/"/>
  </TalendProperties:SQLPatternItem>
</xmi:XMI>
